SenticDB/SenticDB.py
SenticDB/__init__.py
SenticDB-0.1.1.dist-info/LICENSE
SenticDB-0.1.1.dist-info/METADATA
SenticDB-0.1.1.dist-info/WHEEL
SenticDB-0.1.1.dist-info/top_level.txt
SenticDB-0.1.1.dist-info/RECORD
